ciceroscm/__init__.py
ciceroscm/_utils.py
ciceroscm/_version.py
ciceroscm/ciceroscm.py
ciceroscm/component_factory_functions.py
ciceroscm/concentrations_emissions_handler.py
ciceroscm/constants.py
ciceroscm/input_handler.py
ciceroscm/make_plots.py
ciceroscm/perturbations.py
ciceroscm/pub_utils.py
ciceroscm/carbon_cycle/__init__.py
ciceroscm/carbon_cycle/carbon_cycle_abstract.py
ciceroscm/carbon_cycle/carbon_cycle_mod.py
ciceroscm/carbon_cycle/carbon_cycle_mod_box.py
ciceroscm/carbon_cycle/common_carbon_cycle_functions.py
ciceroscm/carbon_cycle/rfuns.py
ciceroscm/default_data/IPCC_LUCalbedo.txt
ciceroscm/default_data/meanVOLCmnd_ipcc_NH.txt
ciceroscm/default_data/solar_IPCC.txt
ciceroscm/formattingtools/reformat_cscm_results.py
ciceroscm/formattingtools/reformat_inputdata_to_cscm_format.py
ciceroscm/parallel/__init__.py
ciceroscm/parallel/_configdistro.py
ciceroscm/parallel/_parallel_process.py
ciceroscm/parallel/cscmparwrapper.py
ciceroscm/parallel/distributionrun.py
ciceroscm/thermal_model/abstract_thermal_model.py
ciceroscm/thermal_model/two_layer_ocean.py
ciceroscm/thermal_model/upwelling_diffusion_model.py
ciceroscm-2.0.1.dist-info/licenses/LICENSE
ciceroscm-2.0.1.dist-info/METADATA
ciceroscm-2.0.1.dist-info/WHEEL
ciceroscm-2.0.1.dist-info/top_level.txt
ciceroscm-2.0.1.dist-info/RECORD
