Metadata-Version: 2.4
Name: ciceroscm
Version: 2.0.1
Summary: Python version of the CICERO-SCM simple climate model
Author-email: Marit Sandstad <marit.sandstad@cicero.oslo.no>, Ragnhild Bieltvedt Skeie <r.b.skeie@cicero.oslo.no>, Ane Nordlie Johansen <ane.nordlie.johansen@cicero.oslo.no>, Benjamin Sanderson <benjamin.sanderson@cicero.oslo.no>
Keywords: cicero-scm,cicero,python,repo,simple,climate,model
Classifier: Development Status :: 4 - Beta
Classifier: License :: OSI Approved :: Apache Software License
Classifier: Intended Audience :: Developers
Classifier: Operating System :: OS Independent
Classifier: Programming Language :: Python :: 3.12
Classifier: Programming Language :: Python :: 3.10
Classifier: Programming Language :: Python :: 3.11
Requires-Python: >=3.10
License-File: LICENSE
Requires-Dist: click
Requires-Dist: python-dotenv
Requires-Dist: tqdm
Requires-Dist: matplotlib>=3.4
Requires-Dist: scipy
Requires-Dist: numpy>=1.23
Requires-Dist: pandas
Provides-Extra: notebooks
Requires-Dist: ipywidgets; extra == "notebooks"
Requires-Dist: notebook; extra == "notebooks"
Requires-Dist: seaborn; extra == "notebooks"
Provides-Extra: tests
Requires-Dist: codecov; extra == "tests"
Requires-Dist: coverage; extra == "tests"
Requires-Dist: nbval; extra == "tests"
Requires-Dist: pytest-cov; extra == "tests"
Requires-Dist: pytest>=4.0; extra == "tests"
Requires-Dist: xlrd; extra == "tests"
Provides-Extra: docs
Requires-Dist: sphinx>=5; extra == "docs"
Requires-Dist: sphinx_rtd_theme; extra == "docs"
Requires-Dist: sphinx-click; extra == "docs"
Provides-Extra: deploy
Requires-Dist: twine>=1.11.0; extra == "deploy"
Requires-Dist: setuptools>=41.2; extra == "deploy"
Requires-Dist: wheel>=0.31.0; extra == "deploy"
Provides-Extra: dev
Requires-Dist: bandit; extra == "dev"
Requires-Dist: black>=22.3.0; extra == "dev"
Requires-Dist: black-nb; extra == "dev"
Requires-Dist: flake8; extra == "dev"
Requires-Dist: isort>5; extra == "dev"
Requires-Dist: mypy; extra == "dev"
Requires-Dist: nbdime; extra == "dev"
Requires-Dist: pydocstyle[toml]; extra == "dev"
Requires-Dist: pylint>=2.4.4; extra == "dev"
Requires-Dist: ruff==0.8.6; extra == "dev"
Requires-Dist: ciceroscm[deploy,docs,notebooks,tests]; extra == "dev"
Dynamic: license-file
